./.env.example
./.gitignore
./LICENSE
./PKG-INFO
./README.md
./figma_mcp.py
./pyproject.toml
./uv.lock
./docs/plans/2026-01-23-mcp-bugfixes.md
./docs/plans/2026-01-30-ai-optimized-css-output.md
./docs/plans/2026-01-30-swiftui-codegen-rewrite.md
./docs/plans/2026-01-31-mcp-codegen-improvements.md
./docs/plans/2026-01-31-v3-bugfixes-design.md
./generators/__init__.py
./generators/base.py
./generators/css_generator.py
./generators/kotlin_generator.py
./generators/react_generator.py
./generators/swiftui_generator.py
./generators/vue_generator.py
pixelbyte_figma_mcp-3.2.9.dist-info/METADATA
pixelbyte_figma_mcp-3.2.9.dist-info/WHEEL
pixelbyte_figma_mcp-3.2.9.dist-info/entry_points.txt
pixelbyte_figma_mcp-3.2.9.dist-info/licenses/LICENSE
pixelbyte_figma_mcp-3.2.9.dist-info/RECORD
