Metadata-Version: 2.4
Name: pixelbyte-figma-mcp
Version: 3.2.9
Summary: MCP Server for Figma API - Design tokens, gradients, effects, interactions, accessibility checks, Code Connect, and code generation for React, Vue, SwiftUI, Kotlin
Project-URL: Homepage, https://github.com/nicepixelbyte/pixelbyte-figma-mcp
Project-URL: Repository, https://github.com/nicepixelbyte/pixelbyte-figma-mcp
Project-URL: Issues, https://github.com/nicepixelbyte/pixelbyte-figma-mcp/issues
Author-email: Yusuf Demirkoparan <yusuf@pixelbyte.dev>
License: MIT
License-File: LICENSE
Keywords: code-connect,code-generation,design-tokens,figma,kotlin,mcp,model-context-protocol,react,swiftui,tailwind
Classifier: Development Status :: 4 - Beta
Classifier: Intended Audience :: Developers
Classifier: License :: OSI Approved :: MIT License
Classifier: Programming Language :: Python :: 3
Classifier: Programming Language :: Python :: 3.10
Classifier: Programming Language :: Python :: 3.11
Classifier: Programming Language :: Python :: 3.12
Classifier: Topic :: Software Development :: Code Generators
Requires-Python: >=3.10
Requires-Dist: httpx>=0.27.0
Requires-Dist: mcp[cli]>=1.0.0
Requires-Dist: pydantic>=2.0.0
